safeserializer/__init__.py
safeserializer/compression.py
safeserializer-0.230202.1.dist-info/LICENSE
safeserializer-0.230202.1.dist-info/METADATA
safeserializer-0.230202.1.dist-info/WHEEL
safeserializer-0.230202.1.dist-info/RECORD
