Metadata-Version: 2.1
Name: safeserializer
Version: 0.230202.1
Summary: Hopefully safe and deterministic serializer to binary format, including Pandas data
License: GPL
Author: davips
Author-email: dpsabc@gmail.com
Requires-Python: >=3.10,<4.0
Classifier: License :: Other/Proprietary License
Classifier: Programming Language :: Python :: 3
Classifier: Programming Language :: Python :: 3.10
Classifier: Programming Language :: Python :: 3.11
Provides-Extra: full
Requires-Dist: dill (>=0.3.6,<0.4.0) ; extra == "full"
Requires-Dist: lz4 (>=4.0.2,<5.0.0) ; extra == "full"
Requires-Dist: orjson (>=3.7.8,<4.0.0)
Requires-Dist: pandas (>=1.4.3,<2.0.0) ; extra == "full"
Requires-Dist: pymongo (>=4.2.0,<5.0.0)
